bitfrog/__init__.py
bitfrog-0.0.8.dist-info/METADATA
bitfrog-0.0.8.dist-info/WHEEL
bitfrog-0.0.8.dist-info/licenses/LICENSE
bitfrog-0.0.8.dist-info/RECORD
