Metadata-Version: 2.4
Name: bitfrog
Version: 0.0.8
Summary: A Python API for Bitfrog notifications.
Project-URL: Homepage, https://github.com/kaighe/bitfrog-python
Project-URL: Issues, https://github.com/kaighe/bitfrog-python/issues
Author-email: Kai Albertson <kaialbertson@gmail.com>
License-Expression: MIT
License-File: LICENSE
Classifier: Operating System :: OS Independent
Classifier: Programming Language :: Python :: 3
Requires-Python: >=3.8
Requires-Dist: requests
